slackwrapper/__init__.py
slackwrapper-1.0.0.dev2.dist-info/LICENSE
slackwrapper-1.0.0.dev2.dist-info/METADATA
slackwrapper-1.0.0.dev2.dist-info/WHEEL
slackwrapper-1.0.0.dev2.dist-info/top_level.txt
slackwrapper-1.0.0.dev2.dist-info/RECORD
